geojson_stats-0.2.9.dist-info/METADATA
geojson_stats-0.2.9.dist-info/WHEEL
geojson_stats-0.2.9.dist-info/entry_points.txt
geojson_stats-0.2.9.dist-info/licenses/LICENSE.md
geojson_stats/.DS_Store
geojson_stats/__init__.py
geojson_stats/__version__.py
geojson_stats/cli.py
geojson_stats/geoutils.py
geojson_stats/html.py
geojson_stats/models.py
geojson_stats/stats.py
geojson_stats-0.2.9.dist-info/RECORD
