Metadata-Version: 2.1
Name: geojson-stats
Version: 0.2.9
Summary: Stats for GeoJSON data
Keywords: hot,geojson,data
Author-Email: Emilio Mariscal <emilio.mariscal@hotosm.org>
License: AGPL-3.0-only
Classifier: Topic :: Utilities
Classifier: Topic :: Scientific/Engineering :: GIS
Classifier: Programming Language :: Python :: 3
Classifier: Programming Language :: Python :: 3.8
Classifier: Programming Language :: Python :: 3.8
Project-URL: homepage, https://github.com/emi420/geojson-stats
Project-URL: documentation, https://github.com/emi420/geojson-stats
Project-URL: repository, https://github.com/emi420/geojson-stats
Requires-Python: >=3.8
Requires-Dist: pyproj>=3.5.0
Requires-Dist: shapely>=1.8.1
